[{"username":"a","post":"카레","date":"2019-04-13T20:52:20.345Z","images":["/images/dff76a5684974dab901e27c78177b98f.jpg","/images/a367280a0704fd5f060cfb77689fa8be.jpg"],"likes":[null],"comments":[{"username":"a","post":"카레는 인도 카레","date":"2019-04-13T20:52:32.882Z","images":"","likes":[],"comments":[]},{"username":"a","post":"카레카레 인도 카레카레","date":"2019-04-13T20:52:41.618Z","images":"","likes":[],"comments":[]}]},{"username":"a","post":"백종원 cook","date":"2019-04-13T20:22:07.204Z","images":["/images/f52e6790562823dfd5c66ff3059d42df.jpg","/images/f8e2e15d90c5c513b199703aa3ebff23.jpg","/images/659cb88ef5eef6e8f319c62a2441e943.jpg"],"likes":[null,null,"a"],"comments":[{"username":"a","post":"asdf","date":"2019-04-13T20:25:44.280Z","images":"","likes":[],"comments":[]},{"username":"a","post":"test comment","date":"2019-04-13T20:51:00.371Z","images":"","likes":[],"comments":[]}]},{"username":"a","post":"TEST 1 2 3 !@#%^&* ","date":"2019-04-12T20:31:36.432Z","images":[],"likes":["a"],"comments":[{"post":"test aaa","date":"2019-04-13T20:17:24.966Z","images":"","likes":[],"comments":[]},{"post":"asdf","date":"2019-04-13T20:17:36.076Z","images":"","likes":[],"comments":[]},{"username":"a","post":"A test","date":"2019-04-13T20:19:24.146Z","images":"","likes":[],"comments":[]}]},{"username":"a","post":"가나다라","date":"2019-04-12T20:31:26.313Z","images":[],"likes":[]},{"username":"a","post":"google Chrome","date":"2019-04-12T20:28:52.877Z","images":[],"likes":["a"],"comments":[{"username":"a","post":"FFFF","date":"2019-04-12T20:51:31.449Z","images":"","likes":[],"comments":[]},{"username":"a","post":"self comments :)","date":"2019-04-12T20:57:00.269Z","images":"","likes":[],"comments":[]}]},{"username":"a","post":"RRRRRRRRRRRRRRRR","date":"2019-04-12T20:28:43.668Z","images":[],"likes":[]},{"username":"a","post":"BBB","date":"2019-04-12T19:53:37.496Z","images":["/images/361266238ddf23f7e98848a7d6673a69.jpg","/images/5130a92fdbdafc409e8329fd6789f261.jpg","/images/763a6460391653d49e1a1724f488a788.jpg"],"likes":[null,"b"]},{"username":"a","post":"A","date":"2019-04-12T19:53:27.530Z","images":[],"likes":["b","a"],"comments":[{"username":"a","post":"VVVVV","date":"2019-04-12T21:05:10.315Z","images":"","likes":[],"comments":[]}]}]